mutalyzer_backtranslate/__init__.py
mutalyzer_backtranslate/backtranslate.py
mutalyzer_backtranslate/cli.py
mutalyzer_backtranslate/util.py
mutalyzer_backtranslate-0.1.4.dist-info/LICENSE.md
mutalyzer_backtranslate-0.1.4.dist-info/METADATA
mutalyzer_backtranslate-0.1.4.dist-info/WHEEL
mutalyzer_backtranslate-0.1.4.dist-info/entry_points.txt
mutalyzer_backtranslate-0.1.4.dist-info/top_level.txt
mutalyzer_backtranslate-0.1.4.dist-info/RECORD
