Metadata-Version: 2.1
Name: mutalyzer-backtranslate
Version: 0.1.4
Summary: Functions for reverse translation.
Home-page: https://github.com/mutalyzer/backtranslate
Author: LUMC, Jeroen F.J. Laros
Author-email: J.F.J.Laros@lumc.nl
License: MIT
Keywords: bioinformatics
Platform: UNKNOWN
Classifier: Intended Audience :: Developers
Classifier: Intended Audience :: Science/Research
Classifier: Operating System :: OS Independent
Classifier: Programming Language :: Python :: 3
Classifier: Programming Language :: Python :: 3.5
Classifier: Programming Language :: Python :: 3.6
Classifier: Topic :: Scientific/Engineering
License-File: LICENSE.md
Requires-Dist: biopython (>=1.76)
Requires-Dist: python-Levenshtein (==0.12.0)
